graph_based_clustering/__init__.py
graph_based_clustering/check.py
graph_based_clustering/main.py
graph_based_clustering/utils.py
tests/__init__.py
tests/test_graph_clustering.py
tests/utils.py
graph_based_clustering-0.1.0.dist-info/LICENSE
graph_based_clustering-0.1.0.dist-info/METADATA
graph_based_clustering-0.1.0.dist-info/WHEEL
graph_based_clustering-0.1.0.dist-info/top_level.txt
graph_based_clustering-0.1.0.dist-info/RECORD
