Metadata-Version: 2.1
Name: graph-based-clustering
Version: 0.1.0
Summary: Graph-Based Clustering using connected components and spanning trees
Home-page: https://github.com/dayyass/graph-based-clustering
Author: Dani El-Ayyass
Author-email: dayyass@yandex.ru
License: UNKNOWN
Project-URL: Bug Tracker, https://github.com/dayyass/graph-based-clustering/issues
Platform: UNKNOWN
Classifier: Programming Language :: Python :: 3
Classifier: License :: OSI Approved :: MIT License
Classifier: Operating System :: OS Independent
Requires-Python: >=3.7
License-File: LICENSE
Requires-Dist: numpy (>=1.21.2)
Requires-Dist: scikit-learn (>=0.24.2)
Requires-Dist: scipy (>=1.7.1)
